{
  "serviceId": "kinkong-trading",
  "name": "KinKong AI Token Trading",
  "description": "Advanced autonomous AI trading system specializing in Solana ecosystem token trading and portfolio management.",
  "fullDescription": "# KinKong: Advanced AI Trading System\n\nKinKong represents the next evolution in autonomous trading systems, leveraging advanced AI and the KinOS infrastructure to execute precision trades in the Solana ecosystem.\n\n## Core Features\n- Advanced market analysis algorithms\n- Real-time data processing\n- Autonomous decision-making\n- Secure transaction execution\n- Performance tracking\n\n## Benefits\n- AI-driven market analysis\n- Automated trading strategies\n- Risk-adjusted position sizing\n- Portfolio optimization\n- Real-time performance monitoring\n\n[Additional details available in documentation]",
  "basePrice": 120000,
  "categories": "[\"Trading\",\"DeFi\",\"AI\",\"Portfolio Management\",\"Analytics\"]",
  "computePerTask": 120000,
  "averageCompletionTime": "real-time",
  "capabilities": "[\"Market Pattern Recognition\",\"Dynamic Strategy Adaptation\",\"Automated Trade Execution\",\"Risk Management\",\"Portfolio Rebalancing\",\"Performance Analytics\"]",
  "serviceType": "financial",
  "swarmId": "kinkong",
  "banner": "/services/kinkong-trading.png",
  "activeSubscriptions": 0
}